candlelite/__init__.py
candlelite/calculate/__init__.py
candlelite/calculate/bar.py
candlelite/calculate/interval.py
candlelite/calculate/technical.py
candlelite/calculate/transform.py
candlelite/calculate/valid.py
candlelite/cmdline/__init__.py
candlelite/crypto/__init__.py
candlelite/crypto/_base.py
candlelite/crypto/binace_lite.py
candlelite/crypto/okx_lite.py
candlelite/exception/__init__.py
candlelite/exception/_base.py
candlelite/exception/candle.py
candlelite/exception/execute.py
candlelite/exception/param.py
candlelite/io/__init__.py
candlelite/io/load.py
candlelite/io/path.py
candlelite/io/save.py
candlelite/settings/__init__.py
candlelite-1.0.17.dist-info/METADATA
candlelite-1.0.17.dist-info/WHEEL
candlelite-1.0.17.dist-info/entry_points.txt
candlelite-1.0.17.dist-info/top_level.txt
candlelite-1.0.17.dist-info/RECORD
